textual_orm/__init__.py
textual_orm/database.py
textual_orm/db_redis.py
textual_orm/errors.py
textual_orm/index.py
textual_orm/libs/__init__.py
textual_orm/libs/base.py
textual_orm/libs/default_llm.py
textual_orm/libs/llm_manager.py
textual_orm/libs/openai.py
textual_orm/libs/sql_generator.py
textual_orm-0.1.3.dist-info/LICENSE
textual_orm-0.1.3.dist-info/METADATA
textual_orm-0.1.3.dist-info/WHEEL
textual_orm-0.1.3.dist-info/top_level.txt
textual_orm-0.1.3.dist-info/RECORD
