Metadata-Version: 2.1
Name: textual_orm
Version: 0.1.3
Summary: SQL Generator and Query Result Retriever
Home-page: https://github.com/kampkelly/TextualOrm
Author: Oghenerunor Adjekpiyede
Author-email: kampkellykeys@gmail.com
License: MIT
Classifier: Development Status :: 4 - Beta
Classifier: Intended Audience :: Developers
Classifier: License :: OSI Approved :: MIT License
Classifier: Programming Language :: Python :: 3.12
Requires-Python: >=3.12
License-File: LICENSE
Requires-Dist: asyncpg ==0.29.0
Requires-Dist: redis[hiredis] ==5.0.8
Requires-Dist: langchain ==0.2.12
Requires-Dist: langchain-huggingface ==0.0.3
Requires-Dist: transformers ==4.44.0
Requires-Dist: langchain-community ==0.2.11
Requires-Dist: peft ==0.12.0
Requires-Dist: torch ==2.4.0
Requires-Dist: langchain-openai ==0.1.21
